ej02/FF_D.v
module FF_D (input clk, reset, enabled, input [3:0] D, output reg [3:0] Q);

    always @ (posedge clk, posedge reset)
        if (reset)
            Q <= 4'b0000;
        else if (enabled)
            Q <= D;
    
endmodule

ej02/ALU.v
module ALU(input [3:0] A, B,
           input [2:0] F,
           output C, Z,
           output [3:0] S);

    reg [4:0] regS;

    always @ (A, B, F)
        case (F)
            3'b000: regS = A;
            3'b001: regS = A - B;
            3'b010: regS = B;
            3'b011: regS = A + B;
            3'b100: regS = {1'b0, ~(A & B)};
            default: regS = 5'b10101;
        endcase

    assign S = regS[3:0];
    assign C = regS[4];
    assign Z = ~(regS[3] | regS[2] | regS[1] | regS[0]);

endmodule

ej02/buffer.v
module buffer(input enabled, input [3:0] A, output [3:0] Y);
    
    assign Y = enabled ? A : 4'bz;
    
endmodule

ej02/ej02.v
//`include "ALU.v"
//`include "buffer.v"
//`include "FF_D.v"

module ej02 (input clk, reset, enBuff1, enBuff2, enAccu,
             input [2:0] F,
             input [3:0] busInput,
             output C,Z,
             output [3:0] busOutput, accu);
    
    wire [3:0] data_bus, aluResult;
    
    // puertos de buffer -> input enabled, input [3:0] A, output [3:0] Y
    buffer U1(enBuff1, busInput, data_bus);
    buffer U2(enBuff2, aluResult, busOutput);
    
    // puertos de ALU -> input [3:0] A, B, input [2:0] F, output C, Z, output [3:0] S
    ALU U3(.A(accu), .B(data_bus), .F(F), .C(C), .Z(Z), .S(aluResult));
    
    // puertos de FF_D -> input clk, reset, enabled, input [3:0] D, output reg [3:0] Q
    FF_D U4(clk, reset, enAccu, aluResult, accu);
    
endmodule

ej02/ej02_tb.v
/*

Para este ejercicio decidí agregar la salida del Accu para poder verificar el 
valor almacenado.

No era necesario para el laboratorio, pero resultó ser muy útil para verificar
la funcionalidad de la ALU.

Una recomendación para hacer estas verificaciones es abrir el programa
GTKWave por aparte y cargar el archivo .vcd del testbench. Hay una opción
que permite hacer un re-load de las gráficas. Esto evita que tengan que arrastrar
las señales cada vez que corran su programa.

El testbench completo está diseñado para usar GTKWave. No hay nada en $monitor

*/

module testbench();
    
    reg clk, reset, buffIn, buffOut, enAccu;
    reg [2:0] F;
    reg [3:0] busInput;
    wire C, Z;
    wire [3:0] busOutput, accu;
    
    ej02 U1 (clk, reset, buffIn, buffOut, enAccu, F, busInput, C, Z, busOutput, accu);
    
    always
        #5 clk = ~clk;
    
    initial
        #200 $finish;
    
    initial begin
        clk = 0; reset = 0; buffIn = 0; buffOut = 0; enAccu = 0; F = 3'b000; busInput = 4'b0000;
        #2 reset = 1;
        #1 reset = 0;
        
        // Almacenar algo en el Accu
        #1
        buffIn = 1;
        buffOut = 1;
        enAccu = 1;
        F = 3'b010;
        busInput = 4'b1010;
        
        // Cambiar la ALU a sumar +1 a cualquier cosa que esté en el Accu
        #10
        busInput = 4'b0001;
        F = 3'b011;
        
        // Deshabilitar el buffer de salidas
        #10
        buffOut = 0;
        
        // Re-habilitar el buffer de salida y deshabilitar el buffer de entrada
        // La ALU sigue sumando por lo que la salida debería ser Accu + 4'bz
        // Esto entrega 4'bxxxx en la salida porque la suma no se puede hacer
        #8
        buffOut = 1;
        #2
        buffIn = 0;
        
        // Cambiar la ALU a dejar pasar el accu. En este momento el Accu debería
        // tener un valor 4'bxxxx.
        #10
        F = 3'b000;
        
        // Guardar el valor 4'b0001 en el Accu y luego cambiar la ALU para dejar
        // pasar el valor del Accu a la salida
        #10
        buffIn = 1;
        F = 3'b010;
        #5
        F = 3'b000;
        
        // Cambiar la ALU para hacer CMPx y restar
        // La resta es 1-1 por lo que la bandera de Z debe levantarse
        // Cuando pasa a F la bandera de C debe levantarse también cuando
        // sea 0 - 1 (A < B)
        #5
        F = 3'b001;
        
        // Para probar Z de forma más extensa podemos dejar pasar 4'b0000 a la ALU
        #30
        busInput = 4'b0000;
        F = 3'b010;
        
        // Cambio a dejar pasar el Accu. Z debe seguir encendido.
        #10
        F = 3'b000;
        
        // Apagar enAccu, dejar pasar B y cambiar el valor de entrada
        #10
        enAccu = 0;
        busInput = 4'b0101;
        F = 3'b010;
        
        // Encender enAccu para almacenar el dato
        #10
        enAccu = 1;
        
        // Por último verificar NANDx. Debe ser ~(0101 & 0101)
        #10
        busInput = 4'b0101;
        F = 3'b100;
        
        // Apagar todas las señales y verificar el valor almacenado en el Accu
        // que debería ser 4'b1010.
        #10
        buffIn = 0;
        buffOut = 1;
        enAccu = 0;
        F = 3'b000;
        
    end
    
    
    initial begin
        $dumpfile("ej02_tb.vcd");
        $dumpvars(0, testbench);
    end

endmodule

ej02/ej02_tb.vcd
$date
	Sun Nov 15 20:04:06 2020
$end
$version
	Icarus Verilog
$end
$timescale
	1ps
$end
$scope module testbench $end
$var wire 4 ! busOutput [3:0] $end
$var wire 4 " accu [3:0] $end
$var wire 1 # Z $end
$var wire 1 $ C $end
$var reg 3 % F [2:0] $end
$var reg 1 & buffIn $end
$var reg 1 ' buffOut $end
$var reg 4 ( busInput [3:0] $end
$var reg 1 ) clk $end
$var reg 1 * enAccu $end
$var reg 1 + reset $end
$scope module U1 $end
$var wire 3 , F [2:0] $end
$var wire 4 - busInput [3:0] $end
$var wire 1 ) clk $end
$var wire 1 * enAccu $end
$var wire 1 & enBuff1 $end
$var wire 1 ' enBuff2 $end
$var wire 1 + reset $end
$var wire 4 . data_bus [3:0] $end
$var wire 4 / busOutput [3:0] $end
$var wire 4 0 aluResult [3:0] $end
$var wire 4 1 accu [3:0] $end
$var wire 1 # Z $end
$var wire 1 $ C $end
$scope module U1 $end
$var wire 4 2 A [3:0] $end
$var wire 1 & enabled $end
$var wire 4 3 Y [3:0] $end
$upscope $end
$scope module U2 $end
$var wire 1 ' enabled $end
$var wire 4 4 Y [3:0] $end
$var wire 4 5 A [3:0] $end
$upscope $end
$scope module U3 $end
$var wire 4 6 B [3:0] $end
$var wire 3 7 F [2:0] $end
$var wire 1 # Z $end
$var wire 4 8 S [3:0] $end
$var wire 1 $ C $end
$var wire 4 9 A [3:0] $end
$var reg 5 : regS [4:0] $end
$upscope $end
$scope module U4 $end
$var wire 4 ; D [3:0] $end
$var wire 1 ) clk $end
$var wire 1 * enabled $end
$var wire 1 + reset $end
$var reg 4 < Q [3:0] $end
$upscope $end
$upscope $end
$upscope $end
$enddefinitions $end
#0
$dumpvars
bx <
bx ;
b0xxxx :
bx 9
bx 8
b0 7
bz 6
bx 5
bz 4
bz 3
b0 2
bx 1
bx 0
bz /
bz .
b0 -
b0 ,
0+
0*
0)
b0 (
0'
0&
b0 %
0$
x#
bx "
bz !
$end
#2
1#
b0 0
b0 5
b0 8
b0 ;
b0 :
b0 "
b0 1
b0 9
b0 <
1+
#3
0+
#4
0#
b1010 0
b1010 5
b1010 8
b1010 ;
b1010 :
b1010 !
b1010 /
b1010 4
b1010 .
b1010 3
b1010 6
b1010 (
b1010 -
b1010 2
b10 %
b10 ,
b10 7
1*
1'
1&
#5
b1010 "
b1010 1
b1010 9
b1010 <
1)
#10
0)
#14
b1011 !
b1011 /
b1011 4
b1011 0
b1011 5
b1011 8
b1011 ;
b1011 :
b1 .
b1 3
b1 6
b11 %
b11 ,
b11 7
b1 (
b1 -
b1 2
#15
b1100 !
b1100 /
b1100 4
b1100 0
b1100 5
b1100 8
b1100 ;
b1100 :
b1011 "
b1011 1
b1011 9
b1011 <
1)
#20
0)
#24
bz !
bz /
bz 4
0'
#25
b1101 0
b1101 5
b1101 8
b1101 ;
b1101 :
b1100 "
b1100 1
b1100 9
b1100 <
1)
#30
0)
#32
b1101 !
b1101 /
b1101 4
1'
#34
x#
bx !
bx /
bx 4
bx 0
bx 5
bx 8
bx ;
x$
bx :
bz .
bz 3
bz 6
0&
#35
bx "
bx 1
bx 9
bx <
1)
#40
0)
#44
0$
b0xxxx :
b0 %
b0 ,
b0 7
#45
1)
#50
0)
#54
0#
b1 !
b1 /
b1 4
b1 0
b1 5
b1 8
b1 ;
b1 :
b1 .
b1 3
b1 6
b10 %
b10 ,
b10 7
1&
#55
b1 "
b1 1
b1 9
b1 <
1)
#59
b0 %
b0 ,
b0 7
#60
0)
#64
1#
b0 !
b0 /
b0 4
b0 0
b0 5
b0 8
b0 ;
b0 :
b1 %
b1 ,
b1 7
#65
0#
b1111 !
b1111 /
b1111 4
b1111 0
b1111 5
b1111 8
b1111 ;
1$
b11111 :
b0 "
b0 1
b0 9
b0 <
1)
#70
0)
#75
b1110 !
b1110 /
b1110 4
b1110 0
b1110 5
b1110 8
b1110 ;
0$
b1110 :
b1111 "
b1111 1
b1111 9
b1111 <
1)
#80
0)
#85
b1101 !
b1101 /
b1101 4
b1101 0
b1101 5
b1101 8
b1101 ;
b1101 :
b1110 "
b1110 1
b1110 9
b1110 <
1)
#90
0)
#94
1#
b0 !
b0 /
b0 4
b0 0
b0 5
b0 8
b0 ;
b0 :
b0 .
b0 3
b0 6
b10 %
b10 ,
b10 7
b0 (
b0 -
b0 2
#95
b0 "
b0 1
b0 9
b0 <
1)
#100
0)
#104
b0 %
b0 ,
b0 7
#105
1)
#110
0)
#114
0#
b101 !
b101 /
b101 4
b101 0
b101 5
b101 8
b101 ;
b101 :
b101 .
b101 3
b101 6
b10 %
b10 ,
b10 7
b101 (
b101 -
b101 2
0*
#115
1)
#120
0)
#124
1*
#125
b101 "
b101 1
b101 9
b101 <
1)
#130
0)
#134
b1010 !
b1010 /
b1010 4
b1010 0
b1010 5
b1010 8
b1010 ;
b1010 :
b100 %
b100 ,
b100 7
#135
b1111 !
b1111 /
b1111 4
b1111 0
b1111 5
b1111 8
b1111 ;
b1111 :
b1010 "
b1010 1
b1010 9
b1010 <
1)
#140
0)
#144
b1010 !
b1010 /
b1010 4
b1010 0
b1010 5
b1010 8
b1010 ;
b1010 :
bz .
bz 3
bz 6
b0 %
b0 ,
b0 7
0*
0&
