ej01/ej01.v
/*

Este ejercicio está implementado completo en 1 sólo archivo .v

Los 3 primeros módulos que componen el ejercicios son (casi) los mismos de los ejercicios
de los laboratorios anteriores.

El último módulo implementa los primeros 3 y luego los conecta con 'wires'.

*/

module counter (input clk, reset, enabled, load, input [11:0] loadData, output reg [11:0] outValue);

    always @ (posedge clk, posedge reset) begin
        if (reset)
            outValue <= 12'b0;
        else if (load)
            outValue <= loadData;
        else if (enabled)
            outValue <= outValue + 1;
    end

endmodule

module ROM (input [11:0] address, output [7:0] data);

    reg [7:0] memory [0:4096];
    
    initial
        $readmemb("memory.list", memory);
    
    assign data = memory[address];

endmodule

module FF_D (input clk, reset, enabled, input [7:0] D, output reg [7:0] Q);

    always @ (posedge clk, posedge reset)
        if (reset)
            Q <= 8'b0000;
        else if (enabled)
            Q <= D;
    
endmodule

module ej01(input clk, reset, enCounter, enFetch, load,
            input [11:0] counter12bit,
            output [3:0] instr, oprnd,
            output [7:0] program_byte);
    
    
    wire [11:0] PC;
    
    // puertos de 'counter' -> input clk, reset, enabled, load, input [11:0] loadData, output reg [11:0] outValue
    counter U1(.clk(clk), .reset(reset), .enabled(enCounter), .load(load), .loadData(counter12bit), .outValue(PC));
    // puertos de 'ROM' -> input [11:0] address, output [7:0] data
    ROM U2 (PC, program_byte);
    // puertos de 'FF_D' -> input clk, reset, enabled, input [7:0] D, output reg [7:0] Q
    FF_D U3 (clk, reset, enFetch, program_byte, {instr, oprnd});
    
endmodule

ej01/ej01_tb.v
module testbench();
    
    reg clk, reset, enCounter, enFetch, load;
    reg [11:0] counter12bit;
    wire [3:0] instr, oprnd;
    wire [7:0] program_byte;
    
    // Puertos del ej01 input clk, reset, enCounter, enFetch, load, input [11:0] counter12bit, output [3:0] instr, oprnd, output [7:0] program_byte
    ej01 U1 (clk, reset, enCounter, enFetch, load, counter12bit, instr, oprnd, program_byte);
    
    always
        #5 clk = ~clk;
    
    initial
        #100 $finish;
        
    initial begin
        $display("");
        $monitor("",);
        clk = 0; reset = 0; enCounter = 0; enFetch = 0; load = 0; counter12bit = 12'h000;
        #2 reset = 1;
        #1 reset = 0;
        
        // Primera prueba será verificar el contador + ROM
        // Esto es sencillamente ver que con cada flanco de reloj se vea un
        // nuevo dato en program_byte. No se agrega un delay de intención.
        // Ya que enFetch = 0 la salida debe ser 4'b0000 todo el tiempo
        enCounter = 1;
        
        // La siguiente prueba es hacer el 'load' del contador.
        // Saltamos a la localidad 0x123.
        // El enCounter lo dejamos a propósito en 1 para verificar que el load
        // tenga preferencia sobre el conteo. Se espera tener el valor de la
        // localidad de memoria 0x123 en el program_byte
        #20
        counter12bit = 12'h123;
        load = 1;
        
        // Se deshabilita el load y se permite el conteo de un par de localidades
        // de memoria.
        // NOTA: En este punto me percaté que las únicas señales que deben
        // estar en la lista de sensibilidad del contador son clk y reset.
        // Si se agrega el bit de load o de los 12 bits de entrada produce resultados
        // que podrían causar conflictos con el procesador. En este momento no
        // he hecho pruebas con el procesador, pero es algo importante que tener
        // en cuenta.
        #10
        load = 0;
        counter12bit = 12'h00A;
        
        // Se deshabilita el conteo y se habilita el Fetch
        // En este momento en instr y oprnd deberían estar los mismos valores
        // que en el program_byte. El program_byte ya no cambia porque el conteo
        // se apagó.
        #10
        enCounter = 0;
        enFetch = 1;
    
    end
        
    initial begin
        $dumpfile("ej01_tb.vcd");
        $dumpvars(0, testbench);
    end
    
endmodule

ej01/ej01_tb.vcd
$date
	Sun Nov 15 20:30:52 2020
$end
$version
	Icarus Verilog
$end
$timescale
	1ps
$end
$scope module testbench $end
$var wire 8 ! program_byte [7:0] $end
$var wire 4 " oprnd [3:0] $end
$var wire 4 # instr [3:0] $end
$var reg 1 $ clk $end
$var reg 12 % counter12bit [11:0] $end
$var reg 1 & enCounter $end
$var reg 1 ' enFetch $end
$var reg 1 ( load $end
$var reg 1 ) reset $end
$scope module U1 $end
$var wire 1 $ clk $end
$var wire 12 * counter12bit [11:0] $end
$var wire 1 & enCounter $end
$var wire 1 ' enFetch $end
$var wire 1 ( load $end
$var wire 1 ) reset $end
$var wire 8 + program_byte [7:0] $end
$var wire 4 , oprnd [3:0] $end
$var wire 4 - instr [3:0] $end
$var wire 12 . PC [11:0] $end
$scope module U1 $end
$var wire 1 $ clk $end
$var wire 1 & enabled $end
$var wire 1 ( load $end
$var wire 12 / loadData [11:0] $end
$var wire 1 ) reset $end
$var reg 12 0 outValue [11:0] $end
$upscope $end
$scope module U2 $end
$var wire 12 1 address [11:0] $end
$var wire 8 2 data [7:0] $end
$upscope $end
$scope module U3 $end
$var wire 8 3 D [7:0] $end
$var wire 1 $ clk $end
$var wire 1 ' enabled $end
$var wire 1 ) reset $end
$var reg 8 4 Q [7:0] $end
$upscope $end
$upscope $end
$upscope $end
$enddefinitions $end
#0
$dumpvars
bx 4
bx 3
bx 2
bx 1
bx 0
b0 /
bx .
bx -
bx ,
bx +
b0 *
0)
0(
0'
0&
b0 %
0$
bx #
bx "
bx !
$end
#2
b0 "
b0 ,
b0 #
b0 -
b11110101 !
b11110101 +
b11110101 2
b11110101 3
b0 .
b0 0
b0 1
b0 4
1)
#3
1&
0)
#5
b1101010 !
b1101010 +
b1101010 2
b1101010 3
b1 .
b1 0
b1 1
1$
#10
0$
#15
b1111 !
b1111 +
b1111 2
b1111 3
b10 .
b10 0
b10 1
1$
#20
0$
#23
1(
b100100011 %
b100100011 *
b100100011 /
#25
b10010110 !
b10010110 +
b10010110 2
b10010110 3
b100100011 .
b100100011 0
b100100011 1
1$
#30
0$
#33
b1010 %
b1010 *
b1010 /
0(
#35
b1101001 !
b1101001 +
b1101001 2
b1101001 3
b100100100 .
b100100100 0
b100100100 1
1$
#40
0$
#43
1'
0&
#45
b1001 "
b1001 ,
b110 #
b110 -
b1101001 4
1$
