solucion/ej03/ej03.v
module ALU (input [2:0] F, input [3:0] A, B, output [3:0] res);

    reg [4:0] tempRes;
    
    always @ (F, A, B) begin
        tempRes = 5'b0;
        case (F)
            3'b000: tempRes = A & B;
            3'b001: tempRes = A | B;
            3'b010: tempRes = A + B;
            3'b011: tempRes = 5'b0;
            3'b100: tempRes = A & ~B;
            3'b101: tempRes = A | ~B;
            3'b110: tempRes = A - B;
            3'b111: begin tempRes = A - B; tempRes = tempRes >> 4; end
            default: tempRes = 5'b00000;
        endcase
    end

    assign res = tempRes;

endmodule

solucion/ej03/ej03_tb.v
module ALU_tb();

    reg [2:0] F;
    reg [3:0] A, B;
    wire [3:0] res;

    ALU U1(.F(F), .A(A), .B(B), .res(res));

    initial begin
        $display("A:\tB:\tF:\t\tres:");
        $monitor("%b\t%b\t%b\t\t%b",A,B,F,res);
        
        $display("--- A < B ---");
           A = 4'b0010; B = 4'b0011; F = 3'b000;
        #1 A = 4'b0010; B = 4'b0011; F = 3'b001;
        #1 A = 4'b0010; B = 4'b0011; F = 3'b010;
        #1 A = 4'b0010; B = 4'b0011; F = 3'b100;
        #1 A = 4'b0010; B = 4'b0011; F = 3'b101;
        #1 A = 4'b0010; B = 4'b0011; F = 3'b110;
        #1 A = 4'b0010; B = 4'b0011; F = 3'b111;
        
        #1 $display("--- A > B ---");
        #1 B = 4'b0010; A = 4'b1100; F = 3'b000;
        #1 B = 4'b0010; A = 4'b1100; F = 3'b001;
        #1 B = 4'b0010; A = 4'b1100; F = 3'b010;
        #1 B = 4'b0010; A = 4'b1100; F = 3'b100;
        #1 B = 4'b0010; A = 4'b1100; F = 3'b101;
        #1 B = 4'b0010; A = 4'b1100; F = 3'b110;
        #1 B = 4'b0010; A = 4'b1100; F = 3'b111;
        
        #1 $display("--- A = B ---");
        #1 B = 4'b0011; A = 4'b0011; F = 3'b000;
        #1 B = 4'b0011; A = 4'b0011; F = 3'b001;
        #1 B = 4'b0011; A = 4'b0011; F = 3'b010;
        #1 B = 4'b0011; A = 4'b0011; F = 3'b100;
        #1 B = 4'b0011; A = 4'b0011; F = 3'b101;
        #1 B = 4'b0011; A = 4'b0011; F = 3'b110;
        #1 B = 4'b0011; A = 4'b0011; F = 3'b111;
    end
    
    initial
        #100 $finish;

    initial begin
        $dumpfile("ej03_tb.vcd");
        $dumpvars(0, ALU_tb);
    end

endmodule

solucion/ej03/ej03_tb.vcd
$date
	Fri Nov 13 23:54:43 2020
$end
$version
	Icarus Verilog
$end
$timescale
	1ps
$end
$scope module ALU_tb $end
$var wire 4 ! res [3:0] $end
$var reg 4 " A [3:0] $end
$var reg 4 # B [3:0] $end
$var reg 3 $ F [2:0] $end
$scope module U1 $end
$var wire 4 % A [3:0] $end
$var wire 4 & B [3:0] $end
$var wire 3 ' F [2:0] $end
$var wire 4 ( res [3:0] $end
$var reg 5 ) tempRes [4:0] $end
$upscope $end
$upscope $end
$enddefinitions $end
#0
$dumpvars
b10 )
b10 (
b0 '
b11 &
b10 %
b0 $
b11 #
b10 "
b10 !
$end
#1
b11 !
b11 (
b11 )
b1 $
b1 '
#2
b101 !
b101 (
b101 )
b10 $
b10 '
#3
b0 !
b0 (
b0 )
b100 $
b100 '
#4
b1110 !
b1110 (
b11110 )
b101 $
b101 '
#5
b1111 !
b1111 (
b11111 )
b110 $
b110 '
#6
b1 !
b1 (
b1 )
b111 $
b111 '
#8
b0 !
b0 (
b0 )
b0 $
b0 '
b1100 "
b1100 %
b10 #
b10 &
#9
b1110 !
b1110 (
b1110 )
b1 $
b1 '
#10
b1110 )
b10 $
b10 '
#11
b1100 !
b1100 (
b1100 )
b100 $
b100 '
#12
b1101 !
b1101 (
b11101 )
b101 $
b101 '
#13
b1010 !
b1010 (
b1010 )
b110 $
b110 '
#14
b0 !
b0 (
b0 )
b111 $
b111 '
#16
b11 !
b11 (
b11 )
b0 $
b0 '
b11 "
b11 %
b11 #
b11 &
#17
b11 )
b1 $
b1 '
#18
b110 !
b110 (
b110 )
b10 $
b10 '
#19
b0 !
b0 (
b0 )
b100 $
b100 '
#20
b1111 !
b1111 (
b11111 )
b101 $
b101 '
#21
b0 !
b0 (
b0 )
b110 $
b110 '
#22
b111 $
b111 '
