solucion/ej01/ej01.v
module counter (input clk, reset, enabled, load, input [11:0] loadData, output reg [11:0] outValue);

    always @ (posedge clk, posedge reset, loadData) begin
        if (reset)
            outValue = 12'b0;
        else if (load)
            outValue = loadData;
        else if (enabled)
            outValue = outValue + 1;
    end

endmodule

solucion/ej01/ej01_tb.v
module counter_tb ();

    reg clk, reset, enabled, load;
    reg [11:0] loadData;
    wire[11:0] outValue;

    counter U1(.clk(clk), .reset(reset), .enabled(enabled), .load(load), .loadData(loadData), .outValue(outValue));

    initial begin
        $display("reset\tenabled\tload\tloadData\t\toutValue");
        $monitor("%b\t%b\t%b\t%b\t\t%b",reset, enabled, load, loadData, outValue);
        clk = 0; reset = 0; enabled = 0; load = 0; loadData = 12'b1100_0011_0101;
        #1 reset = 1;
        #1 reset = 0;
    end
    
    initial begin
        #8 enabled = 1;
        #(52-4) enabled = 0;
        #25 enabled = 1;
        #44 enabled = 0;
    end
    
    initial begin
        #52 load = 1;
        #12 loadData = 12'b1111_0000_1111;
        #12 load = 0;
    end
    
    initial
        #150 $finish;
    
    always
        #5 clk = ~clk;
    
    initial begin
        $dumpfile("ej01_tb.vcd");
        $dumpvars(0, counter_tb);
    end
    
endmodule

solucion/ej01/ej01_tb.vcd
$date
	Fri Nov 13 12:00:31 2020
$end
$version
	Icarus Verilog
$end
$timescale
	1ps
$end
$scope module counter_tb $end
$var wire 12 ! outValue [11:0] $end
$var reg 1 " clk $end
$var reg 1 # enabled $end
$var reg 1 $ load $end
$var reg 12 % loadData [11:0] $end
$var reg 1 & reset $end
$scope module U1 $end
$var wire 1 " clk $end
$var wire 1 # enabled $end
$var wire 1 $ load $end
$var wire 12 ' loadData [11:0] $end
$var wire 1 & reset $end
$var reg 12 ( outValue [11:0] $end
$upscope $end
$upscope $end
$enddefinitions $end
#0
$dumpvars
bx (
b110000110101 '
0&
b110000110101 %
0$
0#
0"
bx !
$end
#1
b0 !
b0 (
1&
#2
0&
#5
1"
#8
1#
#10
0"
#15
b1 !
b1 (
1"
#20
0"
#25
b10 !
b10 (
1"
#30
0"
#35
b11 !
b11 (
1"
#40
0"
#45
b100 !
b100 (
1"
#50
0"
#52
1$
#55
b110000110101 !
b110000110101 (
1"
#56
0#
#60
0"
#64
b111100001111 !
b111100001111 (
b111100001111 %
b111100001111 '
#65
1"
#70
0"
#75
1"
#76
0$
#80
0"
#81
1#
#85
b111100010000 !
b111100010000 (
1"
#90
0"
#95
b111100010001 !
b111100010001 (
1"
#100
0"
#105
b111100010010 !
b111100010010 (
1"
#110
0"
#115
b111100010011 !
b111100010011 (
1"
#120
0"
#125
1"
0#
